README.md
setup.py
nlp_tools/__init__.py
nlp_tools/__version__.py
nlp_tools/generators.py
nlp_tools/logger.py
nlp_tools/macros.py
nlp_tools/types.py
nlp_tools.egg-info/PKG-INFO
nlp_tools.egg-info/SOURCES.txt
nlp_tools.egg-info/dependency_links.txt
nlp_tools.egg-info/not-zip-safe
nlp_tools.egg-info/requires.txt
nlp_tools.egg-info/top_level.txt
nlp_tools/callbacks/__init__.py
nlp_tools/callbacks/eval_callback.py
nlp_tools/callbacks/learning_rate_callback.py
nlp_tools/callbacks/classification/__init__.py
nlp_tools/callbacks/classification/f1score_save_callback.py
nlp_tools/callbacks/embedding/__init__.py
nlp_tools/callbacks/embedding/corrcoef_callback.py
nlp_tools/callbacks/ner/__init__.py
nlp_tools/callbacks/ner/global_pointer_callback.py
nlp_tools/corpus/__init__.py
nlp_tools/corpus/lcqmc.py
nlp_tools/corpus/classify/__init__.py
nlp_tools/corpus/classify/competition.py
nlp_tools/corpus/classify/corpus_loader.py
nlp_tools/corpus/classify/dialogue_corpus_loader.py
nlp_tools/corpus/glue_baseline/__init__.py
nlp_tools/corpus/glue_baseline/sts_b.py
nlp_tools/corpus/ner/__init__.py
nlp_tools/corpus/ner/corpus_loader.py
nlp_tools/corpus/ner/global_pointer/__init__.py
nlp_tools/corpus/ner/global_pointer/cluener_global_pointer_loader.py
nlp_tools/corpus/seq2seq/__init__.py
nlp_tools/corpus/seq2seq/autotitle_thunc.py
nlp_tools/corpus/seq2seq/nlpcc2017textsummarization.py
nlp_tools/corpus/seq2seq/xiaohuangji.py
nlp_tools/corpus/similar/__init__.py
nlp_tools/corpus/similar/tianchi.py
nlp_tools/embeddings/__init__.py
nlp_tools/embeddings/abc_embedding.py
nlp_tools/embeddings/bare_embedding.py
nlp_tools/embeddings/word_embedding.py
nlp_tools/embeddings/hugginface/__init__.py
nlp_tools/embeddings/hugginface/autoembedding.py
nlp_tools/embeddings/hugginface/huggingface_tf_bert_embedding.py
nlp_tools/embeddings/hugginface/prefix_prompt/TFRobertaPrefixEmbedding.py
nlp_tools/embeddings/hugginface/prefix_prompt/__init__.py
nlp_tools/embeddings/hugginface/prefix_prompt/auto_embedding_prefix_embedding.py
nlp_tools/embeddings/hugginface/prefix_prompt/configuration_prefix_prompt_roberta.py
nlp_tools/layers/__init__.py
nlp_tools/layers/att_wgt_avg_layer.py
