Metadata-Version: 2.1
Name: nlp-tools
Version: 1.0
Summary: 工程提取字段相关的一些定义以及一些常用函数封装
Author: qiufengfeng
Author-email: 544855237@qq.com
License: LGPL
Platform: UNKNOWN
